[
  {
    "title": "Réveil",
    "start": "2026-04-09T07:00:00",
    "end": "2026-04-09T09:00:00",
    "source": "Anime (sheet)",
    "url": "",
    "googleSheetUrl": "",
    "location": "",
    "tags": [
      "matin"
    ]
  },
  {
    "title": "Work",
    "start": "2026-04-09T09:00:00",
    "end": "2026-04-09T10:30:00",
    "source": "Anime (sheet)",
    "url": "",
    "googleSheetUrl": "",
    "location": "",
    "tags": [
      "work"
    ]
  },
  {
    "title": "Sport",
    "start": "2026-04-09T10:30:00",
    "end": "2026-04-09T11:30:00",
    "source": "Anime (sheet)",
    "url": "",
    "googleSheetUrl": "",
    "location": "",
    "tags": [
      "sport"
    ]
  },
  {
    "title": "Work",
    "start": "2026-04-09T14:00:00",
    "end": "2026-04-09T15:30:00",
    "source": "Anime (sheet)",
    "url": "",
    "googleSheetUrl": "",
    "location": "",
    "tags": [
      "work"
    ]
  },
  {
    "title": "Dr Stone",
    "start": "2026-04-09T16:30:00",
    "source": "Anime (sheet)",
    "url": "https://mastermanga.github.io/AnimeTrackerV2/",
    "googleSheetUrl": "https://docs.google.com/spreadsheets/d/1WuGg-AH0X1x5ZdOswZlwn5KxE-V0TKeYTxovN20E9UE/edit?gid=15026583#gid=15026583",
    "location": "",
    "tags": [
      "anime"
    ]
  },
  {
    "title": "The Ramparts Of Ice",
    "start": "2026-04-09T18:15:00",
    "source": "Anime (sheet)",
    "url": "https://mastermanga.github.io/AnimeTrackerV2/",
    "googleSheetUrl": "https://docs.google.com/spreadsheets/d/1WuGg-AH0X1x5ZdOswZlwn5KxE-V0TKeYTxovN20E9UE/edit?gid=15026583#gid=15026583",
    "location": "",
    "tags": [
      "anime"
    ]
  },
  {
    "title": "Réveil",
    "start": "2026-04-10T07:00:00",
    "end": "2026-04-10T09:00:00",
    "source": "Anime (sheet)",
    "url": "",
    "googleSheetUrl": "",
    "location": "",
    "tags": [
      "matin"
    ]
  },
  {
    "title": "Work",
    "start": "2026-04-10T09:00:00",
    "end": "2026-04-10T10:30:00",
    "source": "Anime (sheet)",
    "url": "",
    "googleSheetUrl": "",
    "location": "",
    "tags": [
      "work"
    ]
  },
  {
    "title": "Sport",
    "start": "2026-04-10T10:30:00",
    "end": "2026-04-10T11:30:00",
    "source": "Anime (sheet)",
    "url": "",
    "googleSheetUrl": "",
    "location": "",
    "tags": [
      "sport"
    ]
  },
  {
    "title": "Work",
    "start": "2026-04-10T14:00:00",
    "end": "2026-04-10T15:30:00",
    "source": "Anime (sheet)",
    "url": "",
    "googleSheetUrl": "",
    "location": "",
    "tags": [
      "work"
    ]
  },
  {
    "title": "Slime",
    "start": "2026-04-10T17:20:00",
    "source": "Anime (sheet)",
    "url": "https://mastermanga.github.io/AnimeTrackerV2/",
    "googleSheetUrl": "https://docs.google.com/spreadsheets/d/1WuGg-AH0X1x5ZdOswZlwn5KxE-V0TKeYTxovN20E9UE/edit?gid=15026583#gid=15026583",
    "location": "",
    "tags": [
      "anime"
    ]
  },
  {
    "title": "JDR Vallarnia",
    "start": "2026-04-10T19:30:00",
    "source": "Anime (sheet)",
    "url": "",
    "googleSheetUrl": "",
    "location": "",
    "tags": [
      "jdr"
    ]
  },
  {
    "title": "Réveil",
    "start": "2026-04-11T07:00:00",
    "end": "2026-04-11T09:00:00",
    "source": "Anime (sheet)",
    "url": "",
    "googleSheetUrl": "",
    "location": "",
    "tags": [
      "matin"
    ]
  },
  {
    "title": "Work",
    "start": "2026-04-11T09:00:00",
    "end": "2026-04-11T10:30:00",
    "source": "Anime (sheet)",
    "url": "",
    "googleSheetUrl": "",
    "location": "",
    "tags": [
      "work"
    ]
  },
  {
    "title": "Sport",
    "start": "2026-04-11T10:30:00",
    "end": "2026-04-11T11:30:00",
    "source": "Anime (sheet)",
    "url": "",
    "googleSheetUrl": "",
    "location": "",
    "tags": [
      "sport"
    ]
  },
  {
    "title": "Akane Banashi",
    "start": "2026-04-11T18:00:00",
    "source": "Anime (sheet)",
    "url": "https://mastermanga.github.io/AnimeTrackerV2/",
    "googleSheetUrl": "https://docs.google.com/spreadsheets/d/1WuGg-AH0X1x5ZdOswZlwn5KxE-V0TKeYTxovN20E9UE/edit?gid=15026583#gid=15026583",
    "location": "",
    "tags": [
      "anime"
    ]
  },
  {
    "title": "Daemons of the Sadow Realm",
    "start": "2026-04-11T18:20:00",
    "source": "Anime (sheet)",
    "url": "https://mastermanga.github.io/AnimeTrackerV2/",
    "googleSheetUrl": "https://docs.google.com/spreadsheets/d/1WuGg-AH0X1x5ZdOswZlwn5KxE-V0TKeYTxovN20E9UE/edit?gid=15026583#gid=15026583",
    "location": "",
    "tags": [
      "anime"
    ]
  },
  {
    "title": "Agents Of Four Seasons",
    "start": "2026-04-11T19:00:00",
    "source": "Anime (sheet)",
    "url": "https://mastermanga.github.io/AnimeTrackerV2/",
    "googleSheetUrl": "https://docs.google.com/spreadsheets/d/1WuGg-AH0X1x5ZdOswZlwn5KxE-V0TKeYTxovN20E9UE/edit?gid=15026583#gid=15026583",
    "location": "",
    "tags": [
      "anime"
    ]
  },
  {
    "title": "Réveil",
    "start": "2026-04-12T07:00:00",
    "end": "2026-04-12T09:00:00",
    "source": "Anime (sheet)",
    "url": "",
    "googleSheetUrl": "",
    "location": "",
    "tags": [
      "matin"
    ]
  },
  {
    "title": "Work",
    "start": "2026-04-12T09:00:00",
    "end": "2026-04-12T10:30:00",
    "source": "Anime (sheet)",
    "url": "",
    "googleSheetUrl": "",
    "location": "",
    "tags": [
      "work"
    ]
  },
  {
    "title": "Sport",
    "start": "2026-04-12T10:30:00",
    "end": "2026-04-12T11:30:00",
    "source": "Anime (sheet)",
    "url": "",
    "googleSheetUrl": "",
    "location": "",
    "tags": [
      "sport"
    ]
  },
  {
    "title": "Ace Of Diamond",
    "start": "2026-04-12T12:00:00",
    "source": "Anime (sheet)",
    "url": "https://mastermanga.github.io/AnimeTrackerV2/",
    "googleSheetUrl": "https://docs.google.com/spreadsheets/d/1WuGg-AH0X1x5ZdOswZlwn5KxE-V0TKeYTxovN20E9UE/edit?gid=15026583#gid=15026583",
    "location": "",
    "tags": [
      "anime"
    ]
  },
  {
    "title": "One Piece",
    "start": "2026-04-12T20:30:00",
    "source": "Anime (sheet)",
    "url": "https://mastermanga.github.io/AnimeTrackerV2/",
    "googleSheetUrl": "https://docs.google.com/spreadsheets/d/1WuGg-AH0X1x5ZdOswZlwn5KxE-V0TKeYTxovN20E9UE/edit?gid=15026583#gid=15026583",
    "location": "",
    "tags": [
      "anime"
    ]
  },
  {
    "title": "Réveil",
    "start": "2026-04-13T07:00:00",
    "end": "2026-04-13T09:00:00",
    "source": "Anime (sheet)",
    "url": "",
    "googleSheetUrl": "",
    "location": "",
    "tags": [
      "matin"
    ]
  },
  {
    "title": "Work",
    "start": "2026-04-13T09:00:00",
    "end": "2026-04-13T10:30:00",
    "source": "Anime (sheet)",
    "url": "",
    "googleSheetUrl": "",
    "location": "",
    "tags": [
      "work"
    ]
  },
  {
    "title": "Sport",
    "start": "2026-04-13T10:30:00",
    "end": "2026-04-13T11:30:00",
    "source": "Anime (sheet)",
    "url": "",
    "googleSheetUrl": "",
    "location": "",
    "tags": [
      "sport"
    ]
  },
  {
    "title": "Work",
    "start": "2026-04-13T14:00:00",
    "end": "2026-04-13T15:30:00",
    "source": "Anime (sheet)",
    "url": "",
    "googleSheetUrl": "",
    "location": "",
    "tags": [
      "work"
    ]
  },
  {
    "title": "[LEC] Fnatic vs SK Gaming",
    "start": "2026-04-13T15:02:01Z",
    "source": "lolix.gg",
    "url": "https://lolix.gg/predictions",
    "googleSheetUrl": "",
    "location": "",
    "tags": [
      "lolix",
      "esport",
      "lol",
      "lec",
      "fnatic"
    ]
  },
  {
    "title": "[LEC] GIANTX vs Shifters",
    "start": "2026-04-13T17:21:19Z",
    "source": "lolix.gg",
    "url": "https://lolix.gg/predictions",
    "googleSheetUrl": "",
    "location": "",
    "tags": [
      "lolix",
      "esport",
      "lol",
      "lec"
    ]
  },
  {
    "title": "Domingo — PRÉ LIVE",
    "start": "2026-04-13T17:30:00.000Z",
    "end": "2026-04-13T18:00:00.000Z",
    "source": "Twitch:domingo",
    "url": "https://www.twitch.tv/domingo/schedule",
    "googleSheetUrl": "",
    "location": "",
    "tags": [
      "twitch",
      "domingo"
    ]
  },
  {
    "title": "Witch Hat Atelier",
    "start": "2026-04-13T18:00:00",
    "source": "Anime (sheet)",
    "url": "https://mastermanga.github.io/AnimeTrackerV2/",
    "googleSheetUrl": "https://docs.google.com/spreadsheets/d/1WuGg-AH0X1x5ZdOswZlwn5KxE-V0TKeYTxovN20E9UE/edit?gid=15026583#gid=15026583",
    "location": "",
    "tags": [
      "anime"
    ]
  },
  {
    "title": "Domingo — REACT DALS AVEC MARCUS",
    "start": "2026-04-13T18:00:00.000Z",
    "end": "2026-04-13T19:30:00.000Z",
    "source": "Twitch:domingo",
    "url": "https://www.twitch.tv/domingo/schedule",
    "googleSheetUrl": "",
    "location": "",
    "tags": [
      "twitch",
      "domingo"
    ]
  },
  {
    "title": "Domingo — REACT NETFLIX - LES DINOSAURES",
    "start": "2026-04-13T19:30:00.000Z",
    "end": "2026-04-13T22:00:00.000Z",
    "source": "Twitch:domingo",
    "url": "https://www.twitch.tv/domingo/schedule",
    "googleSheetUrl": "",
    "location": "",
    "tags": [
      "twitch",
      "domingo"
    ]
  },
  {
    "title": "Réveil",
    "start": "2026-04-14T07:00:00",
    "end": "2026-04-14T09:00:00",
    "source": "Anime (sheet)",
    "url": "",
    "googleSheetUrl": "",
    "location": "",
    "tags": [
      "matin"
    ]
  },
  {
    "title": "Work",
    "start": "2026-04-14T09:00:00",
    "end": "2026-04-14T10:30:00",
    "source": "Anime (sheet)",
    "url": "",
    "googleSheetUrl": "",
    "location": "",
    "tags": [
      "work"
    ]
  },
  {
    "title": "Sport",
    "start": "2026-04-14T10:30:00",
    "end": "2026-04-14T11:30:00",
    "source": "Anime (sheet)",
    "url": "",
    "googleSheetUrl": "",
    "location": "",
    "tags": [
      "sport"
    ]
  },
  {
    "title": "Work",
    "start": "2026-04-14T14:00:00",
    "end": "2026-04-14T15:30:00",
    "source": "Anime (sheet)",
    "url": "",
    "googleSheetUrl": "",
    "location": "",
    "tags": [
      "work"
    ]
  },
  {
    "title": "Liar Game",
    "start": "2026-04-14T18:00:00",
    "source": "Anime (sheet)",
    "url": "https://mastermanga.github.io/AnimeTrackerV2/",
    "googleSheetUrl": "https://docs.google.com/spreadsheets/d/1WuGg-AH0X1x5ZdOswZlwn5KxE-V0TKeYTxovN20E9UE/edit?gid=15026583#gid=15026583",
    "location": "",
    "tags": [
      "anime"
    ]
  },
  {
    "title": "Marriagetoxin",
    "start": "2026-04-14T18:00:00",
    "source": "Anime (sheet)",
    "url": "https://mastermanga.github.io/AnimeTrackerV2/",
    "googleSheetUrl": "https://docs.google.com/spreadsheets/d/1WuGg-AH0X1x5ZdOswZlwn5KxE-V0TKeYTxovN20E9UE/edit?gid=15026583#gid=15026583",
    "location": "",
    "tags": [
      "anime"
    ]
  },
  {
    "title": "Réveil",
    "start": "2026-04-15T07:00:00",
    "end": "2026-04-15T09:00:00",
    "source": "Anime (sheet)",
    "url": "",
    "googleSheetUrl": "",
    "location": "",
    "tags": [
      "matin"
    ]
  },
  {
    "title": "[LCK] Nongshim Red Force vs BNK FEARX",
    "start": "2026-04-15T07:59:19Z",
    "source": "lolix.gg",
    "url": "https://lolix.gg/predictions",
    "googleSheetUrl": "",
    "location": "",
    "tags": [
      "lolix",
      "esport",
      "lol",
      "lck"
    ]
  },
  {
    "title": "Work",
    "start": "2026-04-15T09:00:00",
    "end": "2026-04-15T10:30:00",
    "source": "Anime (sheet)",
    "url": "",
    "googleSheetUrl": "",
    "location": "",
    "tags": [
      "work"
    ]
  },
  {
    "title": "[LCK] KT Rolster vs Dplus KIA",
    "start": "2026-04-15T10:04:35Z",
    "source": "lolix.gg",
    "url": "https://lolix.gg/predictions",
    "googleSheetUrl": "",
    "location": "",
    "tags": [
      "lolix",
      "esport",
      "lol",
      "lck"
    ]
  },
  {
    "title": "Sport",
    "start": "2026-04-15T10:30:00",
    "end": "2026-04-15T11:30:00",
    "source": "Anime (sheet)",
    "url": "",
    "googleSheetUrl": "",
    "location": "",
    "tags": [
      "sport"
    ]
  },
  {
    "title": "Domingo — PRÉ LIVE",
    "start": "2026-04-15T12:00:00.000Z",
    "end": "2026-04-15T13:00:00.000Z",
    "source": "Twitch:domingo",
    "url": "https://www.twitch.tv/domingo/schedule",
    "googleSheetUrl": "",
    "location": "",
    "tags": [
      "twitch",
      "domingo"
    ]
  },
  {
    "title": "Domingo — ON DÉCOUVRE ALASKA GOLD FEVER",
    "start": "2026-04-15T13:00:00.000Z",
    "end": "2026-04-15T15:00:00.000Z",
    "source": "Twitch:domingo",
    "url": "https://www.twitch.tv/domingo/schedule",
    "googleSheetUrl": "",
    "location": "",
    "tags": [
      "twitch",
      "domingo"
    ]
  },
  {
    "title": "Classroom Of The Elite",
    "start": "2026-04-15T14:00:00",
    "source": "Anime (sheet)",
    "url": "https://mastermanga.github.io/AnimeTrackerV2/",
    "googleSheetUrl": "https://docs.google.com/spreadsheets/d/1WuGg-AH0X1x5ZdOswZlwn5KxE-V0TKeYTxovN20E9UE/edit?gid=15026583#gid=15026583",
    "location": "",
    "tags": [
      "anime"
    ]
  },
  {
    "title": "Work",
    "start": "2026-04-15T14:00:00",
    "end": "2026-04-15T15:30:00",
    "source": "Anime (sheet)",
    "url": "",
    "googleSheetUrl": "",
    "location": "",
    "tags": [
      "work"
    ]
  },
  {
    "title": "Domingo — STREAM LIBRE",
    "start": "2026-04-15T15:00:00.000Z",
    "end": "2026-04-15T17:00:00.000Z",
    "source": "Twitch:domingo",
    "url": "https://www.twitch.tv/domingo/schedule",
    "googleSheetUrl": "",
    "location": "",
    "tags": [
      "twitch",
      "domingo"
    ]
  },
  {
    "title": "Joueur du Grenier — Sponso SINTOPIA",
    "start": "2026-04-15T17:45:00.000Z",
    "end": "2026-04-15T22:00:00.000Z",
    "source": "Twitch:joueur_du_grenier",
    "url": "https://www.twitch.tv/joueur_du_grenier/schedule",
    "googleSheetUrl": "",
    "location": "",
    "tags": [
      "twitch",
      "joueur_du_grenier"
    ]
  },
  {
    "title": "Re:Zero",
    "start": "2026-04-15T18:00:00",
    "source": "Anime (sheet)",
    "url": "https://mastermanga.github.io/AnimeTrackerV2/",
    "googleSheetUrl": "https://docs.google.com/spreadsheets/d/1WuGg-AH0X1x5ZdOswZlwn5KxE-V0TKeYTxovN20E9UE/edit?gid=15026583#gid=15026583",
    "location": "",
    "tags": [
      "anime"
    ]
  },
  {
    "title": "TBATE",
    "start": "2026-04-15T18:45:00",
    "source": "Anime (sheet)",
    "url": "https://mastermanga.github.io/AnimeTrackerV2/",
    "googleSheetUrl": "https://docs.google.com/spreadsheets/d/1WuGg-AH0X1x5ZdOswZlwn5KxE-V0TKeYTxovN20E9UE/edit?gid=15026583#gid=15026583",
    "location": "",
    "tags": [
      "anime"
    ]
  },
  {
    "title": "Réveil",
    "start": "2026-04-16T07:00:00",
    "end": "2026-04-16T09:00:00",
    "source": "Anime (sheet)",
    "url": "",
    "googleSheetUrl": "",
    "location": "",
    "tags": [
      "matin"
    ]
  },
  {
    "title": "[LCK] HANJIN BRION vs Gen.G",
    "start": "2026-04-16T08:00:00Z",
    "source": "lolix.gg",
    "url": "https://lolix.gg/predictions",
    "googleSheetUrl": "",
    "location": "",
    "tags": [
      "lolix",
      "esport",
      "lol",
      "lck",
      "geng"
    ]
  },
  {
    "title": "Work",
    "start": "2026-04-16T09:00:00",
    "end": "2026-04-16T10:30:00",
    "source": "Anime (sheet)",
    "url": "",
    "googleSheetUrl": "",
    "location": "",
    "tags": [
      "work"
    ]
  },
  {
    "title": "[LCK] DN SOOPers vs Hanwha Life Esports",
    "start": "2026-04-16T10:00:00Z",
    "source": "lolix.gg",
    "url": "https://lolix.gg/predictions",
    "googleSheetUrl": "",
    "location": "",
    "tags": [
      "lolix",
      "esport",
      "lol",
      "lck"
    ]
  },
  {
    "title": "Sport",
    "start": "2026-04-16T10:30:00",
    "end": "2026-04-16T11:30:00",
    "source": "Anime (sheet)",
    "url": "",
    "googleSheetUrl": "",
    "location": "",
    "tags": [
      "sport"
    ]
  },
  {
    "title": "Work",
    "start": "2026-04-16T14:00:00",
    "end": "2026-04-16T15:30:00",
    "source": "Anime (sheet)",
    "url": "",
    "googleSheetUrl": "",
    "location": "",
    "tags": [
      "work"
    ]
  },
  {
    "title": "Dr Stone",
    "start": "2026-04-16T16:30:00",
    "source": "Anime (sheet)",
    "url": "https://mastermanga.github.io/AnimeTrackerV2/",
    "googleSheetUrl": "https://docs.google.com/spreadsheets/d/1WuGg-AH0X1x5ZdOswZlwn5KxE-V0TKeYTxovN20E9UE/edit?gid=15026583#gid=15026583",
    "location": "",
    "tags": [
      "anime"
    ]
  },
  {
    "title": "The Ramparts Of Ice",
    "start": "2026-04-16T18:15:00",
    "source": "Anime (sheet)",
    "url": "https://mastermanga.github.io/AnimeTrackerV2/",
    "googleSheetUrl": "https://docs.google.com/spreadsheets/d/1WuGg-AH0X1x5ZdOswZlwn5KxE-V0TKeYTxovN20E9UE/edit?gid=15026583#gid=15026583",
    "location": "",
    "tags": [
      "anime"
    ]
  },
  {
    "title": "Réveil",
    "start": "2026-04-17T07:00:00",
    "end": "2026-04-17T09:00:00",
    "source": "Anime (sheet)",
    "url": "",
    "googleSheetUrl": "",
    "location": "",
    "tags": [
      "matin"
    ]
  },
  {
    "title": "[LCK] Kiwoom DRX vs BNK FEARX",
    "start": "2026-04-17T08:00:00Z",
    "source": "lolix.gg",
    "url": "https://lolix.gg/predictions",
    "googleSheetUrl": "",
    "location": "",
    "tags": [
      "lolix",
      "esport",
      "lol",
      "lck"
    ]
  },
  {
    "title": "Work",
    "start": "2026-04-17T09:00:00",
    "end": "2026-04-17T10:30:00",
    "source": "Anime (sheet)",
    "url": "",
    "googleSheetUrl": "",
    "location": "",
    "tags": [
      "work"
    ]
  },
  {
    "title": "[LCK] Dplus KIA vs T1",
    "start": "2026-04-17T10:00:00Z",
    "source": "lolix.gg",
    "url": "https://lolix.gg/predictions",
    "googleSheetUrl": "",
    "location": "",
    "tags": [
      "lolix",
      "esport",
      "lol",
      "lck"
    ]
  },
  {
    "title": "Sport",
    "start": "2026-04-17T10:30:00",
    "end": "2026-04-17T11:30:00",
    "source": "Anime (sheet)",
    "url": "",
    "googleSheetUrl": "",
    "location": "",
    "tags": [
      "sport"
    ]
  },
  {
    "title": "Work",
    "start": "2026-04-17T14:00:00",
    "end": "2026-04-17T15:30:00",
    "source": "Anime (sheet)",
    "url": "",
    "googleSheetUrl": "",
    "location": "",
    "tags": [
      "work"
    ]
  },
  {
    "title": "Slime",
    "start": "2026-04-17T17:20:00",
    "source": "Anime (sheet)",
    "url": "https://mastermanga.github.io/AnimeTrackerV2/",
    "googleSheetUrl": "https://docs.google.com/spreadsheets/d/1WuGg-AH0X1x5ZdOswZlwn5KxE-V0TKeYTxovN20E9UE/edit?gid=15026583#gid=15026583",
    "location": "",
    "tags": [
      "anime"
    ]
  },
  {
    "title": "Réveil",
    "start": "2026-04-18T07:00:00",
    "end": "2026-04-18T09:00:00",
    "source": "Anime (sheet)",
    "url": "",
    "googleSheetUrl": "",
    "location": "",
    "tags": [
      "matin"
    ]
  },
  {
    "title": "[LCK] Hanwha Life Esports vs Gen.G",
    "start": "2026-04-18T08:00:00Z",
    "source": "lolix.gg",
    "url": "https://lolix.gg/predictions",
    "googleSheetUrl": "",
    "location": "",
    "tags": [
      "lolix",
      "esport",
      "lol",
      "lck",
      "geng"
    ]
  },
  {
    "title": "Work",
    "start": "2026-04-18T09:00:00",
    "end": "2026-04-18T10:30:00",
    "source": "Anime (sheet)",
    "url": "",
    "googleSheetUrl": "",
    "location": "",
    "tags": [
      "work"
    ]
  },
  {
    "title": "[LCK] DN SOOPers vs KT Rolster",
    "start": "2026-04-18T10:00:00Z",
    "source": "lolix.gg",
    "url": "https://lolix.gg/predictions",
    "googleSheetUrl": "",
    "location": "",
    "tags": [
      "lolix",
      "esport",
      "lol",
      "lck"
    ]
  },
  {
    "title": "Sport",
    "start": "2026-04-18T10:30:00",
    "end": "2026-04-18T11:30:00",
    "source": "Anime (sheet)",
    "url": "",
    "googleSheetUrl": "",
    "location": "",
    "tags": [
      "sport"
    ]
  },
  {
    "title": "JDR Ombre",
    "start": "2026-04-18T14:30:00",
    "source": "Anime (sheet)",
    "url": "",
    "googleSheetUrl": "",
    "location": "",
    "tags": [
      "jdr"
    ]
  },
  {
    "title": "[LEC] GIANTX vs Natus Vincere",
    "start": "2026-04-18T15:00:00Z",
    "source": "lolix.gg",
    "url": "https://lolix.gg/predictions",
    "googleSheetUrl": "",
    "location": "",
    "tags": [
      "lolix",
      "esport",
      "lol",
      "lec"
    ]
  },
  {
    "title": "[LEC] G2 Esports vs SK Gaming",
    "start": "2026-04-18T17:15:00Z",
    "source": "lolix.gg",
    "url": "https://lolix.gg/predictions",
    "googleSheetUrl": "",
    "location": "",
    "tags": [
      "lolix",
      "esport",
      "lol",
      "lec"
    ]
  },
  {
    "title": "Joueur du Grenier — Sponso ARKNIGHTS: ENDFIELD",
    "start": "2026-04-18T17:45:00.000Z",
    "end": "2026-04-18T22:00:00.000Z",
    "source": "Twitch:joueur_du_grenier",
    "url": "https://www.twitch.tv/joueur_du_grenier/schedule",
    "googleSheetUrl": "",
    "location": "",
    "tags": [
      "twitch",
      "joueur_du_grenier"
    ]
  },
  {
    "title": "Akane Banashi",
    "start": "2026-04-18T18:00:00",
    "source": "Anime (sheet)",
    "url": "https://mastermanga.github.io/AnimeTrackerV2/",
    "googleSheetUrl": "https://docs.google.com/spreadsheets/d/1WuGg-AH0X1x5ZdOswZlwn5KxE-V0TKeYTxovN20E9UE/edit?gid=15026583#gid=15026583",
    "location": "",
    "tags": [
      "anime"
    ]
  },
  {
    "title": "Daemons of the Sadow Realm",
    "start": "2026-04-18T18:20:00",
    "source": "Anime (sheet)",
    "url": "https://mastermanga.github.io/AnimeTrackerV2/",
    "googleSheetUrl": "https://docs.google.com/spreadsheets/d/1WuGg-AH0X1x5ZdOswZlwn5KxE-V0TKeYTxovN20E9UE/edit?gid=15026583#gid=15026583",
    "location": "",
    "tags": [
      "anime"
    ]
  },
  {
    "title": "Agents Of Four Seasons",
    "start": "2026-04-18T19:00:00",
    "source": "Anime (sheet)",
    "url": "https://mastermanga.github.io/AnimeTrackerV2/",
    "googleSheetUrl": "https://docs.google.com/spreadsheets/d/1WuGg-AH0X1x5ZdOswZlwn5KxE-V0TKeYTxovN20E9UE/edit?gid=15026583#gid=15026583",
    "location": "",
    "tags": [
      "anime"
    ]
  },
  {
    "title": "⚽ [Ligue 1] Lille OSC vs OGC Nice",
    "start": "2026-04-18T19:05:00Z",
    "source": "football-data.org",
    "url": "https://www.football-data.org/",
    "googleSheetUrl": "",
    "location": "",
    "tags": [
      "foot",
      "ligue1",
      "nice"
    ]
  },
  {
    "title": "Réveil",
    "start": "2026-04-19T07:00:00",
    "end": "2026-04-19T09:00:00",
    "source": "Anime (sheet)",
    "url": "",
    "googleSheetUrl": "",
    "location": "",
    "tags": [
      "matin"
    ]
  },
  {
    "title": "[LCK] HANJIN BRION vs Nongshim Red Force",
    "start": "2026-04-19T08:00:00Z",
    "source": "lolix.gg",
    "url": "https://lolix.gg/predictions",
    "googleSheetUrl": "",
    "location": "",
    "tags": [
      "lolix",
      "esport",
      "lol",
      "lck"
    ]
  },
  {
    "title": "Work",
    "start": "2026-04-19T09:00:00",
    "end": "2026-04-19T10:30:00",
    "source": "Anime (sheet)",
    "url": "",
    "googleSheetUrl": "",
    "location": "",
    "tags": [
      "work"
    ]
  },
  {
    "title": "[LCK] Kiwoom DRX vs T1",
    "start": "2026-04-19T10:00:00Z",
    "source": "lolix.gg",
    "url": "https://lolix.gg/predictions",
    "googleSheetUrl": "",
    "location": "",
    "tags": [
      "lolix",
      "esport",
      "lol",
      "lck"
    ]
  },
  {
    "title": "Sport",
    "start": "2026-04-19T10:30:00",
    "end": "2026-04-19T11:30:00",
    "source": "Anime (sheet)",
    "url": "",
    "googleSheetUrl": "",
    "location": "",
    "tags": [
      "sport"
    ]
  },
  {
    "title": "Ace Of Diamond",
    "start": "2026-04-19T12:00:00",
    "source": "Anime (sheet)",
    "url": "https://mastermanga.github.io/AnimeTrackerV2/",
    "googleSheetUrl": "https://docs.google.com/spreadsheets/d/1WuGg-AH0X1x5ZdOswZlwn5KxE-V0TKeYTxovN20E9UE/edit?gid=15026583#gid=15026583",
    "location": "",
    "tags": [
      "anime"
    ]
  },
  {
    "title": "Domingo — KINGS LEAGUE - JOURNÉE 5",
    "start": "2026-04-19T12:30:00.000Z",
    "end": "2026-04-19T17:00:00.000Z",
    "source": "Twitch:domingo",
    "url": "https://www.twitch.tv/domingo/schedule",
    "googleSheetUrl": "",
    "location": "",
    "tags": [
      "twitch",
      "domingo"
    ]
  },
  {
    "title": "⚽ [Premier League] Everton FC vs Liverpool FC",
    "start": "2026-04-19T13:00:00Z",
    "source": "football-data.org",
    "url": "https://www.football-data.org/",
    "googleSheetUrl": "",
    "location": "",
    "tags": [
      "foot",
      "premier_league",
      "liverpool"
    ]
  },
  {
    "title": "[LEC] Team Vitality vs GIANTX",
    "start": "2026-04-19T15:00:00Z",
    "source": "lolix.gg",
    "url": "https://lolix.gg/predictions",
    "googleSheetUrl": "",
    "location": "",
    "tags": [
      "lolix",
      "esport",
      "lol",
      "lec"
    ]
  },
  {
    "title": "⚽ [Premier League] Manchester City FC vs Arsenal FC",
    "start": "2026-04-19T15:30:00Z",
    "source": "football-data.org",
    "url": "https://www.football-data.org/",
    "googleSheetUrl": "",
    "location": "",
    "tags": [
      "foot",
      "premier_league",
      "manchester_city"
    ]
  },
  {
    "title": "⚽ [Bundesliga] FC Bayern München vs VfB Stuttgart",
    "start": "2026-04-19T15:30:00Z",
    "source": "football-data.org",
    "url": "https://www.football-data.org/",
    "googleSheetUrl": "",
    "location": "",
    "tags": [
      "foot",
      "bundesliga",
      "bayern"
    ]
  },
  {
    "title": "[LEC] Team Heretics vs Movistar KOI",
    "start": "2026-04-19T17:15:00Z",
    "source": "lolix.gg",
    "url": "https://lolix.gg/predictions",
    "googleSheetUrl": "",
    "location": "",
    "tags": [
      "lolix",
      "esport",
      "lol",
      "lec"
    ]
  },
  {
    "title": "⚽ [Ligue 1] Paris Saint-Germain FC vs Olympique Lyonnais",
    "start": "2026-04-19T18:45:00Z",
    "source": "football-data.org",
    "url": "https://www.football-data.org/",
    "googleSheetUrl": "",
    "location": "",
    "tags": [
      "foot",
      "ligue1",
      "psg"
    ]
  },
  {
    "title": "One Piece",
    "start": "2026-04-19T20:30:00",
    "source": "Anime (sheet)",
    "url": "https://mastermanga.github.io/AnimeTrackerV2/",
    "googleSheetUrl": "https://docs.google.com/spreadsheets/d/1WuGg-AH0X1x5ZdOswZlwn5KxE-V0TKeYTxovN20E9UE/edit?gid=15026583#gid=15026583",
    "location": "",
    "tags": [
      "anime"
    ]
  },
  {
    "title": "Réveil",
    "start": "2026-04-20T07:00:00",
    "end": "2026-04-20T09:00:00",
    "source": "Anime (sheet)",
    "url": "",
    "googleSheetUrl": "",
    "location": "",
    "tags": [
      "matin"
    ]
  },
  {
    "title": "Work",
    "start": "2026-04-20T09:00:00",
    "end": "2026-04-20T10:30:00",
    "source": "Anime (sheet)",
    "url": "",
    "googleSheetUrl": "",
    "location": "",
    "tags": [
      "work"
    ]
  },
  {
    "title": "Sport",
    "start": "2026-04-20T10:30:00",
    "end": "2026-04-20T11:30:00",
    "source": "Anime (sheet)",
    "url": "",
    "googleSheetUrl": "",
    "location": "",
    "tags": [
      "sport"
    ]
  },
  {
    "title": "Work",
    "start": "2026-04-20T14:00:00",
    "end": "2026-04-20T15:30:00",
    "source": "Anime (sheet)",
    "url": "",
    "googleSheetUrl": "",
    "location": "",
    "tags": [
      "work"
    ]
  },
  {
    "title": "[LEC] Shifters vs G2 Esports",
    "start": "2026-04-20T15:00:00Z",
    "source": "lolix.gg",
    "url": "https://lolix.gg/predictions",
    "googleSheetUrl": "",
    "location": "",
    "tags": [
      "lolix",
      "esport",
      "lol",
      "lec"
    ]
  },
  {
    "title": "[LEC] SK Gaming vs Karmine Corp",
    "start": "2026-04-20T17:15:00Z",
    "source": "lolix.gg",
    "url": "https://lolix.gg/predictions",
    "googleSheetUrl": "",
    "location": "",
    "tags": [
      "lolix",
      "esport",
      "lol",
      "lec"
    ]
  },
  {
    "title": "Witch Hat Atelier",
    "start": "2026-04-20T18:00:00",
    "source": "Anime (sheet)",
    "url": "https://mastermanga.github.io/AnimeTrackerV2/",
    "googleSheetUrl": "https://docs.google.com/spreadsheets/d/1WuGg-AH0X1x5ZdOswZlwn5KxE-V0TKeYTxovN20E9UE/edit?gid=15026583#gid=15026583",
    "location": "",
    "tags": [
      "anime"
    ]
  },
  {
    "title": "Réveil",
    "start": "2026-04-21T07:00:00",
    "end": "2026-04-21T09:00:00",
    "source": "Anime (sheet)",
    "url": "",
    "googleSheetUrl": "",
    "location": "",
    "tags": [
      "matin"
    ]
  },
  {
    "title": "Work",
    "start": "2026-04-21T09:00:00",
    "end": "2026-04-21T10:30:00",
    "source": "Anime (sheet)",
    "url": "",
    "googleSheetUrl": "",
    "location": "",
    "tags": [
      "work"
    ]
  },
  {
    "title": "Sport",
    "start": "2026-04-21T10:30:00",
    "end": "2026-04-21T11:30:00",
    "source": "Anime (sheet)",
    "url": "",
    "googleSheetUrl": "",
    "location": "",
    "tags": [
      "sport"
    ]
  },
  {
    "title": "Work",
    "start": "2026-04-21T14:00:00",
    "end": "2026-04-21T15:30:00",
    "source": "Anime (sheet)",
    "url": "",
    "googleSheetUrl": "",
    "location": "",
    "tags": [
      "work"
    ]
  },
  {
    "title": "Liar Game",
    "start": "2026-04-21T18:00:00",
    "source": "Anime (sheet)",
    "url": "https://mastermanga.github.io/AnimeTrackerV2/",
    "googleSheetUrl": "https://docs.google.com/spreadsheets/d/1WuGg-AH0X1x5ZdOswZlwn5KxE-V0TKeYTxovN20E9UE/edit?gid=15026583#gid=15026583",
    "location": "",
    "tags": [
      "anime"
    ]
  },
  {
    "title": "Marriagetoxin",
    "start": "2026-04-21T18:00:00",
    "source": "Anime (sheet)",
    "url": "https://mastermanga.github.io/AnimeTrackerV2/",
    "googleSheetUrl": "https://docs.google.com/spreadsheets/d/1WuGg-AH0X1x5ZdOswZlwn5KxE-V0TKeYTxovN20E9UE/edit?gid=15026583#gid=15026583",
    "location": "",
    "tags": [
      "anime"
    ]
  },
  {
    "title": "⚽ [Primera Division] Real Madrid CF vs Deportivo Alavés",
    "start": "2026-04-21T19:30:00Z",
    "source": "football-data.org",
    "url": "https://www.football-data.org/",
    "googleSheetUrl": "",
    "location": "",
    "tags": [
      "foot",
      "liga",
      "real_madrid"
    ]
  },
  {
    "title": "Réveil",
    "start": "2026-04-22T07:00:00",
    "end": "2026-04-22T09:00:00",
    "source": "Anime (sheet)",
    "url": "",
    "googleSheetUrl": "",
    "location": "",
    "tags": [
      "matin"
    ]
  },
  {
    "title": "[LCK] KT Rolster vs Kiwoom DRX",
    "start": "2026-04-22T08:00:00Z",
    "source": "lolix.gg",
    "url": "https://lolix.gg/predictions",
    "googleSheetUrl": "",
    "location": "",
    "tags": [
      "lolix",
      "esport",
      "lol",
      "lck"
    ]
  },
  {
    "title": "Work",
    "start": "2026-04-22T09:00:00",
    "end": "2026-04-22T10:30:00",
    "source": "Anime (sheet)",
    "url": "",
    "googleSheetUrl": "",
    "location": "",
    "tags": [
      "work"
    ]
  },
  {
    "title": "[LCK] Hanwha Life Esports vs Nongshim Red Force",
    "start": "2026-04-22T10:00:00Z",
    "source": "lolix.gg",
    "url": "https://lolix.gg/predictions",
    "googleSheetUrl": "",
    "location": "",
    "tags": [
      "lolix",
      "esport",
      "lol",
      "lck"
    ]
  },
  {
    "title": "Sport",
    "start": "2026-04-22T10:30:00",
    "end": "2026-04-22T11:30:00",
    "source": "Anime (sheet)",
    "url": "",
    "googleSheetUrl": "",
    "location": "",
    "tags": [
      "sport"
    ]
  },
  {
    "title": "Classroom Of The Elite",
    "start": "2026-04-22T14:00:00",
    "source": "Anime (sheet)",
    "url": "https://mastermanga.github.io/AnimeTrackerV2/",
    "googleSheetUrl": "https://docs.google.com/spreadsheets/d/1WuGg-AH0X1x5ZdOswZlwn5KxE-V0TKeYTxovN20E9UE/edit?gid=15026583#gid=15026583",
    "location": "",
    "tags": [
      "anime"
    ]
  },
  {
    "title": "Work",
    "start": "2026-04-22T14:00:00",
    "end": "2026-04-22T15:30:00",
    "source": "Anime (sheet)",
    "url": "",
    "googleSheetUrl": "",
    "location": "",
    "tags": [
      "work"
    ]
  },
  {
    "title": "⚽ [Ligue 1] Paris Saint-Germain FC vs FC Nantes",
    "start": "2026-04-22T17:00:00Z",
    "source": "football-data.org",
    "url": "https://www.football-data.org/",
    "googleSheetUrl": "",
    "location": "",
    "tags": [
      "foot",
      "ligue1",
      "psg"
    ]
  },
  {
    "title": "Re:Zero",
    "start": "2026-04-22T18:00:00",
    "source": "Anime (sheet)",
    "url": "https://mastermanga.github.io/AnimeTrackerV2/",
    "googleSheetUrl": "https://docs.google.com/spreadsheets/d/1WuGg-AH0X1x5ZdOswZlwn5KxE-V0TKeYTxovN20E9UE/edit?gid=15026583#gid=15026583",
    "location": "",
    "tags": [
      "anime"
    ]
  },
  {
    "title": "TBATE",
    "start": "2026-04-22T18:45:00",
    "source": "Anime (sheet)",
    "url": "https://mastermanga.github.io/AnimeTrackerV2/",
    "googleSheetUrl": "https://docs.google.com/spreadsheets/d/1WuGg-AH0X1x5ZdOswZlwn5KxE-V0TKeYTxovN20E9UE/edit?gid=15026583#gid=15026583",
    "location": "",
    "tags": [
      "anime"
    ]
  },
  {
    "title": "⚽ [Premier League] Burnley FC vs Manchester City FC",
    "start": "2026-04-22T19:00:00Z",
    "source": "football-data.org",
    "url": "https://www.football-data.org/",
    "googleSheetUrl": "",
    "location": "",
    "tags": [
      "foot",
      "premier_league",
      "manchester_city"
    ]
  },
  {
    "title": "⚽ [Primera Division] FC Barcelona vs RC Celta de Vigo",
    "start": "2026-04-22T19:30:00Z",
    "source": "football-data.org",
    "url": "https://www.football-data.org/",
    "googleSheetUrl": "",
    "location": "",
    "tags": [
      "foot",
      "liga",
      "barcelone"
    ]
  },
  {
    "title": "Réveil",
    "start": "2026-04-23T07:00:00",
    "end": "2026-04-23T09:00:00",
    "source": "Anime (sheet)",
    "url": "",
    "googleSheetUrl": "",
    "location": "",
    "tags": [
      "matin"
    ]
  },
  {
    "title": "[LCK] HANJIN BRION vs Dplus KIA",
    "start": "2026-04-23T08:00:00Z",
    "source": "lolix.gg",
    "url": "https://lolix.gg/predictions",
    "googleSheetUrl": "",
    "location": "",
    "tags": [
      "lolix",
      "esport",
      "lol",
      "lck"
    ]
  },
  {
    "title": "Joueur du Grenier — Sponso FF14",
    "start": "2026-04-23T08:30:00.000Z",
    "end": "2026-04-23T17:30:00.000Z",
    "source": "Twitch:joueur_du_grenier",
    "url": "https://www.twitch.tv/joueur_du_grenier/schedule",
    "googleSheetUrl": "",
    "location": "",
    "tags": [
      "twitch",
      "joueur_du_grenier"
    ]
  },
  {
    "title": "Work",
    "start": "2026-04-23T09:00:00",
    "end": "2026-04-23T10:30:00",
    "source": "Anime (sheet)",
    "url": "",
    "googleSheetUrl": "",
    "location": "",
    "tags": [
      "work"
    ]
  },
  {
    "title": "[LCK] Gen.G vs DN SOOPers",
    "start": "2026-04-23T10:00:00Z",
    "source": "lolix.gg",
    "url": "https://lolix.gg/predictions",
    "googleSheetUrl": "",
    "location": "",
    "tags": [
      "lolix",
      "esport",
      "lol",
      "lck",
      "geng"
    ]
  },
  {
    "title": "Sport",
    "start": "2026-04-23T10:30:00",
    "end": "2026-04-23T11:30:00",
    "source": "Anime (sheet)",
    "url": "",
    "googleSheetUrl": "",
    "location": "",
    "tags": [
      "sport"
    ]
  },
  {
    "title": "Work",
    "start": "2026-04-23T14:00:00",
    "end": "2026-04-23T15:30:00",
    "source": "Anime (sheet)",
    "url": "",
    "googleSheetUrl": "",
    "location": "",
    "tags": [
      "work"
    ]
  },
  {
    "title": "Dr Stone",
    "start": "2026-04-23T16:30:00",
    "source": "Anime (sheet)",
    "url": "https://mastermanga.github.io/AnimeTrackerV2/",
    "googleSheetUrl": "https://docs.google.com/spreadsheets/d/1WuGg-AH0X1x5ZdOswZlwn5KxE-V0TKeYTxovN20E9UE/edit?gid=15026583#gid=15026583",
    "location": "",
    "tags": [
      "anime"
    ]
  },
  {
    "title": "The Ramparts Of Ice",
    "start": "2026-04-23T18:15:00",
    "source": "Anime (sheet)",
    "url": "https://mastermanga.github.io/AnimeTrackerV2/",
    "googleSheetUrl": "https://docs.google.com/spreadsheets/d/1WuGg-AH0X1x5ZdOswZlwn5KxE-V0TKeYTxovN20E9UE/edit?gid=15026583#gid=15026583",
    "location": "",
    "tags": [
      "anime"
    ]
  },
  {
    "title": "Réveil",
    "start": "2026-04-24T07:00:00",
    "end": "2026-04-24T09:00:00",
    "source": "Anime (sheet)",
    "url": "",
    "googleSheetUrl": "",
    "location": "",
    "tags": [
      "matin"
    ]
  },
  {
    "title": "Joueur du Grenier — Sponso FF14",
    "start": "2026-04-24T08:30:00.000Z",
    "end": "2026-04-24T17:30:00.000Z",
    "source": "Twitch:joueur_du_grenier",
    "url": "https://www.twitch.tv/joueur_du_grenier/schedule",
    "googleSheetUrl": "",
    "location": "",
    "tags": [
      "twitch",
      "joueur_du_grenier"
    ]
  },
  {
    "title": "Work",
    "start": "2026-04-24T09:00:00",
    "end": "2026-04-24T10:30:00",
    "source": "Anime (sheet)",
    "url": "",
    "googleSheetUrl": "",
    "location": "",
    "tags": [
      "work"
    ]
  },
  {
    "title": "Sport",
    "start": "2026-04-24T10:30:00",
    "end": "2026-04-24T11:30:00",
    "source": "Anime (sheet)",
    "url": "",
    "googleSheetUrl": "",
    "location": "",
    "tags": [
      "sport"
    ]
  },
  {
    "title": "Work",
    "start": "2026-04-24T14:00:00",
    "end": "2026-04-24T15:30:00",
    "source": "Anime (sheet)",
    "url": "",
    "googleSheetUrl": "",
    "location": "",
    "tags": [
      "work"
    ]
  },
  {
    "title": "Slime",
    "start": "2026-04-24T17:20:00",
    "source": "Anime (sheet)",
    "url": "https://mastermanga.github.io/AnimeTrackerV2/",
    "googleSheetUrl": "https://docs.google.com/spreadsheets/d/1WuGg-AH0X1x5ZdOswZlwn5KxE-V0TKeYTxovN20E9UE/edit?gid=15026583#gid=15026583",
    "location": "",
    "tags": [
      "anime"
    ]
  },
  {
    "title": "⚽ [Primera Division] Real Betis Balompié vs Real Madrid CF",
    "start": "2026-04-24T19:00:00Z",
    "source": "football-data.org",
    "url": "https://www.football-data.org/",
    "googleSheetUrl": "",
    "location": "",
    "tags": [
      "foot",
      "liga",
      "real_madrid"
    ]
  },
  {
    "title": "Réveil",
    "start": "2026-04-25T07:00:00",
    "end": "2026-04-25T09:00:00",
    "source": "Anime (sheet)",
    "url": "",
    "googleSheetUrl": "",
    "location": "",
    "tags": [
      "matin"
    ]
  },
  {
    "title": "Joueur du Grenier — Sponso FF14",
    "start": "2026-04-25T08:30:00.000Z",
    "end": "2026-04-25T17:30:00.000Z",
    "source": "Twitch:joueur_du_grenier",
    "url": "https://www.twitch.tv/joueur_du_grenier/schedule",
    "googleSheetUrl": "",
    "location": "",
    "tags": [
      "twitch",
      "joueur_du_grenier"
    ]
  },
  {
    "title": "Work",
    "start": "2026-04-25T09:00:00",
    "end": "2026-04-25T10:30:00",
    "source": "Anime (sheet)",
    "url": "",
    "googleSheetUrl": "",
    "location": "",
    "tags": [
      "work"
    ]
  },
  {
    "title": "Sport",
    "start": "2026-04-25T10:30:00",
    "end": "2026-04-25T11:30:00",
    "source": "Anime (sheet)",
    "url": "",
    "googleSheetUrl": "",
    "location": "",
    "tags": [
      "sport"
    ]
  },
  {
    "title": "⚽ [Bundesliga] 1. FSV Mainz 05 vs FC Bayern München",
    "start": "2026-04-25T13:30:00Z",
    "source": "football-data.org",
    "url": "https://www.football-data.org/",
    "googleSheetUrl": "",
    "location": "",
    "tags": [
      "foot",
      "bundesliga",
      "bayern"
    ]
  },
  {
    "title": "⚽ [Premier League] Liverpool FC vs Crystal Palace FC",
    "start": "2026-04-25T14:00:00Z",
    "source": "football-data.org",
    "url": "https://www.football-data.org/",
    "googleSheetUrl": "",
    "location": "",
    "tags": [
      "foot",
      "premier_league",
      "liverpool"
    ]
  },
  {
    "title": "⚽ [Primera Division] Getafe CF vs FC Barcelona",
    "start": "2026-04-25T14:15:00Z",
    "source": "football-data.org",
    "url": "https://www.football-data.org/",
    "googleSheetUrl": "",
    "location": "",
    "tags": [
      "foot",
      "liga",
      "barcelone"
    ]
  },
  {
    "title": "⚽ [Ligue 1] Angers SCO vs Paris Saint-Germain FC",
    "start": "2026-04-25T17:00:00Z",
    "source": "football-data.org",
    "url": "https://www.football-data.org/",
    "googleSheetUrl": "",
    "location": "",
    "tags": [
      "foot",
      "ligue1",
      "psg"
    ]
  },
  {
    "title": "Akane Banashi",
    "start": "2026-04-25T18:00:00",
    "source": "Anime (sheet)",
    "url": "https://mastermanga.github.io/AnimeTrackerV2/",
    "googleSheetUrl": "https://docs.google.com/spreadsheets/d/1WuGg-AH0X1x5ZdOswZlwn5KxE-V0TKeYTxovN20E9UE/edit?gid=15026583#gid=15026583",
    "location": "",
    "tags": [
      "anime"
    ]
  },
  {
    "title": "Daemons of the Sadow Realm",
    "start": "2026-04-25T18:20:00",
    "source": "Anime (sheet)",
    "url": "https://mastermanga.github.io/AnimeTrackerV2/",
    "googleSheetUrl": "https://docs.google.com/spreadsheets/d/1WuGg-AH0X1x5ZdOswZlwn5KxE-V0TKeYTxovN20E9UE/edit?gid=15026583#gid=15026583",
    "location": "",
    "tags": [
      "anime"
    ]
  },
  {
    "title": "Agents Of Four Seasons",
    "start": "2026-04-25T19:00:00",
    "source": "Anime (sheet)",
    "url": "https://mastermanga.github.io/AnimeTrackerV2/",
    "googleSheetUrl": "https://docs.google.com/spreadsheets/d/1WuGg-AH0X1x5ZdOswZlwn5KxE-V0TKeYTxovN20E9UE/edit?gid=15026583#gid=15026583",
    "location": "",
    "tags": [
      "anime"
    ]
  },
  {
    "title": "Réveil",
    "start": "2026-04-26T07:00:00",
    "end": "2026-04-26T09:00:00",
    "source": "Anime (sheet)",
    "url": "",
    "googleSheetUrl": "",
    "location": "",
    "tags": [
      "matin"
    ]
  },
  {
    "title": "Joueur du Grenier — Sponso FF14",
    "start": "2026-04-26T08:30:00.000Z",
    "end": "2026-04-26T17:30:00.000Z",
    "source": "Twitch:joueur_du_grenier",
    "url": "https://www.twitch.tv/joueur_du_grenier/schedule",
    "googleSheetUrl": "",
    "location": "",
    "tags": [
      "twitch",
      "joueur_du_grenier"
    ]
  },
  {
    "title": "Work",
    "start": "2026-04-26T09:00:00",
    "end": "2026-04-26T10:30:00",
    "source": "Anime (sheet)",
    "url": "",
    "googleSheetUrl": "",
    "location": "",
    "tags": [
      "work"
    ]
  },
  {
    "title": "Sport",
    "start": "2026-04-26T10:30:00",
    "end": "2026-04-26T11:30:00",
    "source": "Anime (sheet)",
    "url": "",
    "googleSheetUrl": "",
    "location": "",
    "tags": [
      "sport"
    ]
  },
  {
    "title": "Ace Of Diamond",
    "start": "2026-04-26T12:00:00",
    "source": "Anime (sheet)",
    "url": "https://mastermanga.github.io/AnimeTrackerV2/",
    "googleSheetUrl": "https://docs.google.com/spreadsheets/d/1WuGg-AH0X1x5ZdOswZlwn5KxE-V0TKeYTxovN20E9UE/edit?gid=15026583#gid=15026583",
    "location": "",
    "tags": [
      "anime"
    ]
  },
  {
    "title": "⚽ [Ligue 1] Olympique de Marseille vs OGC Nice",
    "start": "2026-04-26T18:45:00Z",
    "source": "football-data.org",
    "url": "https://www.football-data.org/",
    "googleSheetUrl": "",
    "location": "",
    "tags": [
      "foot",
      "ligue1",
      "nice"
    ]
  },
  {
    "title": "One Piece",
    "start": "2026-04-26T20:30:00",
    "source": "Anime (sheet)",
    "url": "https://mastermanga.github.io/AnimeTrackerV2/",
    "googleSheetUrl": "https://docs.google.com/spreadsheets/d/1WuGg-AH0X1x5ZdOswZlwn5KxE-V0TKeYTxovN20E9UE/edit?gid=15026583#gid=15026583",
    "location": "",
    "tags": [
      "anime"
    ]
  },
  {
    "title": "Réveil",
    "start": "2026-04-27T07:00:00",
    "end": "2026-04-27T09:00:00",
    "source": "Anime (sheet)",
    "url": "",
    "googleSheetUrl": "",
    "location": "",
    "tags": [
      "matin"
    ]
  },
  {
    "title": "Work",
    "start": "2026-04-27T09:00:00",
    "end": "2026-04-27T10:30:00",
    "source": "Anime (sheet)",
    "url": "",
    "googleSheetUrl": "",
    "location": "",
    "tags": [
      "work"
    ]
  },
  {
    "title": "Sport",
    "start": "2026-04-27T10:30:00",
    "end": "2026-04-27T11:30:00",
    "source": "Anime (sheet)",
    "url": "",
    "googleSheetUrl": "",
    "location": "",
    "tags": [
      "sport"
    ]
  },
  {
    "title": "Work",
    "start": "2026-04-27T14:00:00",
    "end": "2026-04-27T15:30:00",
    "source": "Anime (sheet)",
    "url": "",
    "googleSheetUrl": "",
    "location": "",
    "tags": [
      "work"
    ]
  },
  {
    "title": "Witch Hat Atelier",
    "start": "2026-04-27T18:00:00",
    "source": "Anime (sheet)",
    "url": "https://mastermanga.github.io/AnimeTrackerV2/",
    "googleSheetUrl": "https://docs.google.com/spreadsheets/d/1WuGg-AH0X1x5ZdOswZlwn5KxE-V0TKeYTxovN20E9UE/edit?gid=15026583#gid=15026583",
    "location": "",
    "tags": [
      "anime"
    ]
  },
  {
    "title": "⚽ [UEFA Champions League] Paris Saint-Germain FC vs FC Bayern München",
    "start": "2026-04-28T00:00:00Z",
    "source": "football-data.org",
    "url": "https://www.football-data.org/",
    "googleSheetUrl": "",
    "location": "",
    "tags": [
      "foot",
      "ldc",
      "psg",
      "bayern"
    ]
  },
  {
    "title": "Réveil",
    "start": "2026-04-28T07:00:00",
    "end": "2026-04-28T09:00:00",
    "source": "Anime (sheet)",
    "url": "",
    "googleSheetUrl": "",
    "location": "",
    "tags": [
      "matin"
    ]
  },
  {
    "title": "Work",
    "start": "2026-04-28T09:00:00",
    "end": "2026-04-28T10:30:00",
    "source": "Anime (sheet)",
    "url": "",
    "googleSheetUrl": "",
    "location": "",
    "tags": [
      "work"
    ]
  },
  {
    "title": "Sport",
    "start": "2026-04-28T10:30:00",
    "end": "2026-04-28T11:30:00",
    "source": "Anime (sheet)",
    "url": "",
    "googleSheetUrl": "",
    "location": "",
    "tags": [
      "sport"
    ]
  },
  {
    "title": "Work",
    "start": "2026-04-28T14:00:00",
    "end": "2026-04-28T15:30:00",
    "source": "Anime (sheet)",
    "url": "",
    "googleSheetUrl": "",
    "location": "",
    "tags": [
      "work"
    ]
  },
  {
    "title": "Liar Game",
    "start": "2026-04-28T18:00:00",
    "source": "Anime (sheet)",
    "url": "https://mastermanga.github.io/AnimeTrackerV2/",
    "googleSheetUrl": "https://docs.google.com/spreadsheets/d/1WuGg-AH0X1x5ZdOswZlwn5KxE-V0TKeYTxovN20E9UE/edit?gid=15026583#gid=15026583",
    "location": "",
    "tags": [
      "anime"
    ]
  },
  {
    "title": "Marriagetoxin",
    "start": "2026-04-28T18:00:00",
    "source": "Anime (sheet)",
    "url": "https://mastermanga.github.io/AnimeTrackerV2/",
    "googleSheetUrl": "https://docs.google.com/spreadsheets/d/1WuGg-AH0X1x5ZdOswZlwn5KxE-V0TKeYTxovN20E9UE/edit?gid=15026583#gid=15026583",
    "location": "",
    "tags": [
      "anime"
    ]
  },
  {
    "title": "Réveil",
    "start": "2026-04-29T07:00:00",
    "end": "2026-04-29T09:00:00",
    "source": "Anime (sheet)",
    "url": "",
    "googleSheetUrl": "",
    "location": "",
    "tags": [
      "matin"
    ]
  },
  {
    "title": "Work",
    "start": "2026-04-29T09:00:00",
    "end": "2026-04-29T10:30:00",
    "source": "Anime (sheet)",
    "url": "",
    "googleSheetUrl": "",
    "location": "",
    "tags": [
      "work"
    ]
  },
  {
    "title": "Sport",
    "start": "2026-04-29T10:30:00",
    "end": "2026-04-29T11:30:00",
    "source": "Anime (sheet)",
    "url": "",
    "googleSheetUrl": "",
    "location": "",
    "tags": [
      "sport"
    ]
  },
  {
    "title": "Classroom Of The Elite",
    "start": "2026-04-29T14:00:00",
    "source": "Anime (sheet)",
    "url": "https://mastermanga.github.io/AnimeTrackerV2/",
    "googleSheetUrl": "https://docs.google.com/spreadsheets/d/1WuGg-AH0X1x5ZdOswZlwn5KxE-V0TKeYTxovN20E9UE/edit?gid=15026583#gid=15026583",
    "location": "",
    "tags": [
      "anime"
    ]
  },
  {
    "title": "Work",
    "start": "2026-04-29T14:00:00",
    "end": "2026-04-29T15:30:00",
    "source": "Anime (sheet)",
    "url": "",
    "googleSheetUrl": "",
    "location": "",
    "tags": [
      "work"
    ]
  },
  {
    "title": "Re:Zero",
    "start": "2026-04-29T18:00:00",
    "source": "Anime (sheet)",
    "url": "https://mastermanga.github.io/AnimeTrackerV2/",
    "googleSheetUrl": "https://docs.google.com/spreadsheets/d/1WuGg-AH0X1x5ZdOswZlwn5KxE-V0TKeYTxovN20E9UE/edit?gid=15026583#gid=15026583",
    "location": "",
    "tags": [
      "anime"
    ]
  },
  {
    "title": "TBATE",
    "start": "2026-04-29T18:45:00",
    "source": "Anime (sheet)",
    "url": "https://mastermanga.github.io/AnimeTrackerV2/",
    "googleSheetUrl": "https://docs.google.com/spreadsheets/d/1WuGg-AH0X1x5ZdOswZlwn5KxE-V0TKeYTxovN20E9UE/edit?gid=15026583#gid=15026583",
    "location": "",
    "tags": [
      "anime"
    ]
  },
  {
    "title": "⚽ [Bundesliga] FC Bayern München vs 1. FC Heidenheim 1846",
    "start": "2026-05-02T13:30:00Z",
    "source": "football-data.org",
    "url": "https://www.football-data.org/",
    "googleSheetUrl": "",
    "location": "",
    "tags": [
      "foot",
      "bundesliga",
      "bayern"
    ]
  },
  {
    "title": "⚽ [Ligue 1] Paris Saint-Germain FC vs FC Lorient",
    "start": "2026-05-02T15:00:00Z",
    "source": "football-data.org",
    "url": "https://www.football-data.org/",
    "googleSheetUrl": "",
    "location": "",
    "tags": [
      "foot",
      "ligue1",
      "psg"
    ]
  },
  {
    "title": "⚽ [Ligue 1] OGC Nice vs Racing Club de Lens",
    "start": "2026-05-02T19:05:00Z",
    "source": "football-data.org",
    "url": "https://www.football-data.org/",
    "googleSheetUrl": "",
    "location": "",
    "tags": [
      "foot",
      "ligue1",
      "nice"
    ]
  },
  {
    "title": "⚽ [Primera Division] RCD Espanyol de Barcelona vs Real Madrid CF",
    "start": "2026-05-03T00:00:00Z",
    "source": "football-data.org",
    "url": "https://www.football-data.org/",
    "googleSheetUrl": "",
    "location": "",
    "tags": [
      "foot",
      "liga",
      "real_madrid"
    ]
  },
  {
    "title": "⚽ [Primera Division] CA Osasuna vs FC Barcelona",
    "start": "2026-05-03T00:00:00Z",
    "source": "football-data.org",
    "url": "https://www.football-data.org/",
    "googleSheetUrl": "",
    "location": "",
    "tags": [
      "foot",
      "liga",
      "barcelone"
    ]
  },
  {
    "title": "⚽ [Premier League] Manchester United FC vs Liverpool FC",
    "start": "2026-05-03T14:30:00Z",
    "source": "football-data.org",
    "url": "https://www.football-data.org/",
    "googleSheetUrl": "",
    "location": "",
    "tags": [
      "foot",
      "premier_league",
      "liverpool"
    ]
  },
  {
    "title": "⚽ [Premier League] Everton FC vs Manchester City FC",
    "start": "2026-05-04T19:00:00Z",
    "source": "football-data.org",
    "url": "https://www.football-data.org/",
    "googleSheetUrl": "",
    "location": "",
    "tags": [
      "foot",
      "premier_league",
      "manchester_city"
    ]
  },
  {
    "title": "⚽ [UEFA Champions League] FC Bayern München vs Paris Saint-Germain FC",
    "start": "2026-05-05T00:00:00Z",
    "source": "football-data.org",
    "url": "https://www.football-data.org/",
    "googleSheetUrl": "",
    "location": "",
    "tags": [
      "foot",
      "ldc",
      "bayern",
      "psg"
    ]
  },
  {
    "title": "⚽ [Premier League] Liverpool FC vs Chelsea FC",
    "start": "2026-05-09T11:30:00Z",
    "source": "football-data.org",
    "url": "https://www.football-data.org/",
    "googleSheetUrl": "",
    "location": "",
    "tags": [
      "foot",
      "premier_league",
      "liverpool"
    ]
  },
  {
    "title": "⚽ [Premier League] Manchester City FC vs Brentford FC",
    "start": "2026-05-09T16:30:00Z",
    "source": "football-data.org",
    "url": "https://www.football-data.org/",
    "googleSheetUrl": "",
    "location": "",
    "tags": [
      "foot",
      "premier_league",
      "manchester_city"
    ]
  },
  {
    "title": "⚽ [Bundesliga] VfL Wolfsburg vs FC Bayern München",
    "start": "2026-05-09T16:30:00Z",
    "source": "football-data.org",
    "url": "https://www.football-data.org/",
    "googleSheetUrl": "",
    "location": "",
    "tags": [
      "foot",
      "bundesliga",
      "bayern"
    ]
  },
  {
    "title": "⚽ [Ligue 1] AJ Auxerre vs OGC Nice",
    "start": "2026-05-09T19:00:00Z",
    "source": "football-data.org",
    "url": "https://www.football-data.org/",
    "googleSheetUrl": "",
    "location": "",
    "tags": [
      "foot",
      "ligue1",
      "nice"
    ]
  },
  {
    "title": "⚽ [Ligue 1] Paris Saint-Germain FC vs Stade Brestois 29",
    "start": "2026-05-09T19:00:00Z",
    "source": "football-data.org",
    "url": "https://www.football-data.org/",
    "googleSheetUrl": "",
    "location": "",
    "tags": [
      "foot",
      "ligue1",
      "psg"
    ]
  },
  {
    "title": "⚽ [Primera Division] FC Barcelona vs Real Madrid CF",
    "start": "2026-05-10T19:00:00Z",
    "source": "football-data.org",
    "url": "https://www.football-data.org/",
    "googleSheetUrl": "",
    "location": "",
    "tags": [
      "foot",
      "liga",
      "barcelone",
      "real_madrid"
    ]
  },
  {
    "title": "⚽ [Primera Division] Deportivo Alavés vs FC Barcelona",
    "start": "2026-05-13T00:00:00Z",
    "source": "football-data.org",
    "url": "https://www.football-data.org/",
    "googleSheetUrl": "",
    "location": "",
    "tags": [
      "foot",
      "liga",
      "barcelone"
    ]
  },
  {
    "title": "⚽ [Primera Division] Real Madrid CF vs Real Oviedo",
    "start": "2026-05-13T00:00:00Z",
    "source": "football-data.org",
    "url": "https://www.football-data.org/",
    "googleSheetUrl": "",
    "location": "",
    "tags": [
      "foot",
      "liga",
      "real_madrid"
    ]
  },
  {
    "title": "⚽ [Ligue 1] Racing Club de Lens vs Paris Saint-Germain FC",
    "start": "2026-05-13T00:00:00Z",
    "source": "football-data.org",
    "url": "https://www.football-data.org/",
    "googleSheetUrl": "",
    "location": "",
    "tags": [
      "foot",
      "ligue1",
      "psg"
    ]
  },
  {
    "title": "⚽ [Bundesliga] FC Bayern München vs 1. FC Köln",
    "start": "2026-05-16T13:30:00Z",
    "source": "football-data.org",
    "url": "https://www.football-data.org/",
    "googleSheetUrl": "",
    "location": "",
    "tags": [
      "foot",
      "bundesliga",
      "bayern"
    ]
  },
  {
    "title": "⚽ [Ligue 1] Paris FC vs Paris Saint-Germain FC",
    "start": "2026-05-16T19:00:00Z",
    "source": "football-data.org",
    "url": "https://www.football-data.org/",
    "googleSheetUrl": "",
    "location": "",
    "tags": [
      "foot",
      "ligue1",
      "psg"
    ]
  },
  {
    "title": "⚽ [Ligue 1] OGC Nice vs FC Metz",
    "start": "2026-05-16T19:00:00Z",
    "source": "football-data.org",
    "url": "https://www.football-data.org/",
    "googleSheetUrl": "",
    "location": "",
    "tags": [
      "foot",
      "ligue1",
      "nice"
    ]
  },
  {
    "title": "⚽ [Primera Division] FC Barcelona vs Real Betis Balompié",
    "start": "2026-05-17T00:00:00Z",
    "source": "football-data.org",
    "url": "https://www.football-data.org/",
    "googleSheetUrl": "",
    "location": "",
    "tags": [
      "foot",
      "liga",
      "barcelone"
    ]
  },
  {
    "title": "⚽ [Primera Division] Sevilla FC vs Real Madrid CF",
    "start": "2026-05-17T00:00:00Z",
    "source": "football-data.org",
    "url": "https://www.football-data.org/",
    "googleSheetUrl": "",
    "location": "",
    "tags": [
      "foot",
      "liga",
      "real_madrid"
    ]
  }
]